games_of_probability/__init__.py
games_of_probability-2.0.0.dist-info/licenses/LICENSE
games_of_probability-2.0.0.dist-info/METADATA
games_of_probability-2.0.0.dist-info/WHEEL
games_of_probability-2.0.0.dist-info/top_level.txt
games_of_probability-2.0.0.dist-info/RECORD
