Metadata-Version: 2.4
Name: games_of_probability
Version: 2.0.0
Summary: Provides classes that are used as games of chance and things that based on probability, using the `random` module.
Author-email: Ngô Trần Quang Thiện <quangthienngotran@gmail.com>
License: GPLv3
Keywords: game,games,probability,chance
Requires-Python: >=3.7
License-File: LICENSE
Dynamic: license-file
